IIIFingest/__init__.py
IIIFingest/asset.py
IIIFingest/auth.py
IIIFingest/bucket.py
IIIFingest/client.py
IIIFingest/generate_manifest.py
IIIFingest/ingest.py
IIIFingest/settings.py
IIIFingest-1.3.0.dist-info/LICENSE.md
IIIFingest-1.3.0.dist-info/METADATA
IIIFingest-1.3.0.dist-info/WHEEL
IIIFingest-1.3.0.dist-info/top_level.txt
IIIFingest-1.3.0.dist-info/RECORD
