Metadata-Version: 2.1
Name: IIIFingest
Version: 1.3.0
Summary: A wrapper library for interacting with the MPS ingest system for IIIF resources
Home-page: https://github.com/Harvard-ATG/lts-iiif-ingest-service
Author: Cole Crawford
Author-email: cole_crawford@fas.harvard.edu
Project-URL: Bug Tracker, https://github.com/Harvard-ATG/lts-iiif-ingest-service/issues
Classifier: Programming Language :: Python :: 3
Classifier: Operating System :: OS Independent
Classifier: License :: OSI Approved :: Apache Software License
Requires-Python: >=3.7
License-File: LICENSE.md
Requires-Dist: pyjwt (~=2.4)
Requires-Dist: cryptography (<42.0,>=3.3)
Requires-Dist: jsonschema (~=4.15)
Requires-Dist: boto3 (~=1.26)
Requires-Dist: Pillow (<11.0,>=9.3)
Requires-Dist: requests (~=2.28)
Requires-Dist: shortuuid (~=1.0)
Requires-Dist: pyIIIFpres (~=0.1)
Requires-Dist: python-magic (~=0.4)
Requires-Dist: Deprecated (~=1.2)
Requires-Dist: backports.zoneinfo (~=0.2) ; python_version < "3.9"
Provides-Extra: all
Requires-Dist: pre-commit (<4.0,>=2.20) ; extra == 'all'
Requires-Dist: isort (~=5.10) ; extra == 'all'
Requires-Dist: black (<24.0,>=22.8) ; extra == 'all'
Requires-Dist: flake8 (<7,>=5) ; extra == 'all'
Requires-Dist: python-dotenv (<2.0,>=0.21) ; extra == 'all'
Requires-Dist: moto (~=4.0) ; extra == 'all'
Requires-Dist: pytest (~=7.1) ; extra == 'all'
Requires-Dist: pytest-mock (~=3.8) ; extra == 'all'
Requires-Dist: pytest-dotenv (~=0.5) ; extra == 'all'
Requires-Dist: build (~=0.9) ; extra == 'all'
Provides-Extra: dev
Requires-Dist: pre-commit (<4.0,>=2.20) ; extra == 'dev'
Requires-Dist: isort (~=5.10) ; extra == 'dev'
Requires-Dist: black (<24.0,>=22.8) ; extra == 'dev'
Requires-Dist: flake8 (<7,>=5) ; extra == 'dev'
Requires-Dist: python-dotenv (<2.0,>=0.21) ; extra == 'dev'
Requires-Dist: moto (~=4.0) ; extra == 'dev'
Requires-Dist: pytest (~=7.1) ; extra == 'dev'
Requires-Dist: pytest-mock (~=3.8) ; extra == 'dev'
Requires-Dist: pytest-dotenv (~=0.5) ; extra == 'dev'
Requires-Dist: build (~=0.9) ; extra == 'dev'
